{"SK-A-4830": ["ochre", "range", "damask", "pewter", "silver", "table", "yellow", "bread, loaf", "grey", "glass", "compliment", "glass of wine", "banquet", "mother", "molluscs: oyster", "interplay", "palette", "heda"], "SK-A-4821": ["pewter", "haarlem", "extending", "cheese", "bread", "table", "fruit", "painter", "edge", "van", "plate", "type", "floris", "painting", "reality", "illusion", "dijck"], "SK-A-3059": ["scene", "body", "portrayal", "patient, sick person", "amsterdam", "virgin", "plague", "back", "representation", "background", "pieta", "time", "s", "wall", "ten", "grey", "child", "son", "lap", "painting", "suffering", "poignant", "crucifixion", "picture, painting"], "SK-A-1627": ["lievens", "workshop", "strength", "delilah", "s", "influence", "rembrandt", "rendering", "hair", "lap", "man", "secret", "work", "source", "samson", "asleep", "pair", "lay"], "SK-A-1451": ["kitchen-personnel", "Christ in the house of Martha and Mary (Luke 10:38-42)"], "SK-A-4646": ["banquet piece", "painter", "asia", "mace", "porcelain", "beginning", "instance", "pieter", "century", "ginger", "fruit", "plate", "claesz", "savoury", "molluscs: oyster", "shell", "cinnamon", "cloves", "presence"], "SK-A-137": ["glass of wine", "fruits: lemon"], "SK-A-4820": ["candlelight", "novelty", "genre", "artist", "scene", "become", "vermeyen", "night", "effect", "leaf", "the apostle John the Evangelist; possible attributes: book, cauldron, chalice with snake, eagle, palm, scroll - vocation, conversion of male saint", "time", "caravaggio", "nocturn"], "SK-C-1458": ["altarpiece", "king", "jesus", "adoration", "baby", "magi", "panel"], "SK-A-335": ["crustaceans: lobster", "laid table as still life", "fruits"], "SK-A-3988": ["banquet piece", "molluscs: oyster", "pipe ~ tobacco", "glass, rummer"], "RP-P-H-1086": ["'Vanitas' still life", "book", "candle"], "SK-A-671": ["adoration of the kings: the Wise Men present their gifts to the Christ-child (gold, frankincense and myrrh)", "palace", "extent", "spectator", "baby", "birth", "lowly", "jesus", "adoration", "painting", "david", "king", "magi"], "SK-A-1751": ["fruit", "fruits: pear", "fruits: medlar", "fruits: pomegranate", "glass, rummer (FLUTE"], "SK-A-4867": ["king", "beginning", "philip", "sovereign", "anjou", "ii", "task", "arch", "ruler", "baldachin", "triumphal arch", "antwerp", "honour", "regime", "brother", "fran\u00e7ois", "duke"], "SK-A-4052": ["indentation", "eroticism", "moment", "undressing oneself, getting undressed", "girl", "peak", "chamber-pot", "left", "viewer", "undressing", "skirt", "bare", "clothing for the upper part of the body (+ fur used for clothes)", "dog", "stocking", "knee", "image", "bed", "underskirt", "garter", "legs"], "SK-A-718": ["cat", "wind", "music", "man", "instrument", "shawm", "protest", "something", "dog", "barking", "window"], "SK-C-206": ["painter", "bull", "grey", "dutch", "vantage", "painting", "role", "sky", "sinewy", "point", "potter", "work", "meadow, pasture", "cloudy"], "SK-A-385": ["foreground", "sugar-candy", "december", "weeping", "wailing", "way", "storyteller", "instance", "feast", "girl", "saint", "left", "picture", "(playing with) dolls", "jan", "steen", "place", "switch", "bundle", "boy", "communal rooms", "bucket", "shoe"], "SK-A-4717": [], "SK-A-390": ["painter", "bread", "couple", "life", "baker", "depiction", "back", "wife", "bread, loaf", "s", "profession", "name", "son", "jan", "painting", "steen", "portrait", "inscription", "boy"], "SK-A-3467": ["deathbed", "book", "preparation", "departure", "death", "sprinkler", "water", "candle", "bed", "set-ting", "middle", "twelve", "virgin", "peter", "centre"], "SK-C-187": ["fruit", "watch", "molluscs: oyster"], "SK-C-301": ["lobster", "monkeys, apes", "pie", "chimneypiece", "pasty", "point", "anything", "ornamental birds: parrot", "fruit", "glass", "plate", "painting", "crustaceans: lobster", "dog", "notation of music", "utrecht", "tableware", "van", "vantage", "meant", "adriaen", "fleming"], "SK-A-2180": ["backgammon, tric-trac", "nursing, suckling"], "SK-C-149": ["kakstoel", "foreground", "dutch", "room", "'motherly care', delousing", "head", "box", "child", "interior", "chair", "garden", "doorway", "glimpse", "lice", "dog", "right", "mother", "task", "bed", "picture, painting"], "SK-C-152": ["cat", "physician, doctor", "patient, sick person", "examination of urine", "foot-stove"], "SK-C-147": ["letter, envelope", "door", "entrance", "gateway", "window", "woman", "converse", "pieter", "canal", "hall", "side", "house", "interior", "whip", "open door", "letter", "dog", "gaze", "right", "exterior", "view", "daylight", "child (at home"], "SK-A-180": ["convincing", "violin, fiddle", "laughing", "tapestry", "order", "man", "surprise", "frame", "fiddler", "window", "s", "painting", "viewer", "glass of wine", "clothing"], "SK-A-4981": ["delft", "woman", "element", "alms", "canal", "surety", "arm", "catharina", "debt", "beggar", "child", "house", "merchant", "croeser", "jan", "grain", "village street", "steen", "oude", "akimbo", "portrait", "stoop", "beg", "daughter"], "SK-A-3518": ["money", "book", "wedding", "engagement", "merchant", "merchant, salesman", "wheel", "man", "dutch", "pair", "counting, calculating", "woman", "s", "housewife", "couple", "historical persons"], "SK-A-86": ["pipe ~ tobacco", "space", "deception", "master", "rod", "sill", "man", "pipe", "painting", "dou", "illusionism", "size", "book", "ledge", "copper", "curtain", "window"], "SK-A-3924": ["firm", "carnation", "amsterdam", "fugger", "life", "transience", "city", "representative", "skull", "house", "banking", "existence", "pompeius", "flowers: carnation", "role", "business", "family", "hope", "augsburg", "occo"], "SK-A-690": ["vermeer", "dutch", "light", "amsterdam", "paris", "style", "writing tools", "s", "master", "ter", "man", "example", "painting", "work", "genre", "use", "borch", "sharpening pen (quill"], "SK-A-3962": ["spinning-wheel", "scene", "woman", "couple", "depiction", "message", "tankard", "wheel", "man", "clothes, costume (+ men's clothes)", "spindle", "clothes, costume (+ women's clothes)", "portrait", "vice", "virtue"], "SK-C-229": ["wind", "pipe ~ tobacco", "story", "grandmother", "note", "moral", "sing", "pipe", "example", "glass", "instrument", "chime", "top", "dog", "glass of wine", "mother", "family", "mantelpiece", "lot", "father", "family life at home", "noise", "twitter", "musician accompanying singer"], "SK-A-2344": ["milkmaid", "vermeer", "activity", "room", "woman", "statue", "pours", "eye", "everything", "subject", "bread, loaf", "stream", "milk", "surface", "painting", "work", "kitchen-maid, kitchen servant", "foot-stove"], "SK-A-3948": ["viola, violoncello; double bass", "music", "room", "art", "drawing, sketch", "amsterdam", "armorial bearing, heraldry", "face", "century", "powder", "shoulder", "viewer", "sitter", "visit", "man", "member", "portrait", "family", "likeness", "gentleman", "distance", "lack", "wig", "globe"], "SK-C-1672": ["painter", "garden vase", "buckle", "society", "fashion", "assink", "skirt", "setting", "belt", "puff", "dog", "kruseman", "silhouette", "waist", "hunting", "hoop", "vase", "portraiture", "clothing"], "SK-A-4941": ["kind", "tale", "painter", "'fahrende Leute', vagrants", "dutch", "scene", "fishes", "meaning", "fraai", "child and art", "mieris", "bird in a cage", "willem", "romance", "manner", "curieus", "peepshow", "painting", "performer", "van", "title", "triptych", "minstrel, 'jongleur"], "SK-A-2205": ["'Vanitas' still life", "book", "hourglass"], "SK-A-3930": ["instruments", "paintbrush", "painter", "impression", "illusion", "foot", "violin, fiddle", "transience", "table", "message", "armour", "cast", "skull", "drawings", "spinario", "reality", "thorn", "antique", "sculpture", "'Vanitas' still life", "painting", "study", "plaster", "world", "boy", "palette"], "SK-C-535": ["scene", "teacher", "woman", "sense", "old woman", "meal", "tablecloth", "self-control", "attention", "essence", "rembrandt", "cat", "duty", "maes", "distract", "virtue", "lighting", "hourglass"], "SK-A-4908": ["helmet", "loyalty", "fort", "watch", "storming", "molluscs: snail", "life", "pocket", "skull", "ivy", "time", "brother", "insects: butterfly", "england", "painting", "dog", "portrait", "death", "languard", "eternity", "felixstowe", "navy", "hourglass"], "SK-A-4290": [], "SK-A-4152": ["evening meal, dinner, supper", "pope"], "SK-C-185": ["painter", "scene", "seller", "poultry", "wall", "willem", "basket", "shop, store", "pendant", "hence", "painting", "member", "right", "egg", "grandfather", "family", "van", "father", "view"], "SK-A-263": [], "SK-A-4157": ["pipe ~ tobacco", "painter in non-work situation"], "SK-A-752": [], "SK-A-1857": ["laid table as still life"], "SK-A-662": ["bookdealer", "painter", "backdrop", "hanging", "scene", "publisher", "banner", "printer", "amsterdam", "print", "bookbinding", "owner", "actor", "city", "press", "perspective", "stage", "floor", "shop", "printing", "paper", "activities", "reams", "book", "book-shop, bookseller", "view"], "SK-A-1595": ["hangings and drapery", "foreground", "letter, envelope", "vermeer", "scene", "sea", "maidservant", "room", "woman", "space", "century", "subject", "seascape", "ship", "s", "wall", "point", "letter", "lover", "painting", "glimpse", "vantage", "picture, painting"], "SK-A-4054": ["eye", "depiction", "gravedigger", "foreground", "eminent", "interior of church", "columns", "through-view", "background", "distance", "painting", "church", "witte", "citizens", "grave digger", "speciality"], "SK-A-4968": ["kind", "firm", "door", "sultan", "regime", "authority", "trees: palm-tree", "reference", "mangkoe", "advertisement", "carriage", "ruler", "painting", "colonial", "coach", "coat", "haaxman", "iv", "co"], "SK-A-2388": ["canals, waters (in city)"], "SK-A-4163": ["cow", "sheep"], "SK-A-4118": ["waal", "scene", "cleves", "landscape", "drawn", "resting", "workshop", "cuyp", "river", "water", "nijmegen", "dordrecht", "herder", "horse", "cattle", "distance", "cow", "italy"], "SK-C-177": ["kind", "woman", "meaning", "bird", "century", "hunter", "cupid", "vogelen", "subject", "intercourse", "s", "hunter displaying or presenting the spoils of the hunt", "cupboard", "ornamental cupboard", "painting", "love", "sewing", "statuette", "god"], "SK-C-112": ["quiringh", "shop", "kind", "century", "tailor, dressmaker", "van", "platform", "river", "brekelenkam", "frame", "tailor", "workshop-interior", "landscape", "work"], "SK-C-134": [], "SK-A-98": [], "SK-A-113": [], "SK-A-1649": [], "SK-A-3103": ["merchant shipping, shipping trade", "printed matter", "historical persons"], "SK-A-3254": ["marketing, shopping (~ household management)", "vegetables"], "SK-A-3995": [], "SK-A-2565": ["sheet", "music", "finis", "life", "lute", "symbol", "s", "composition", "reference", "wall", "grey", "end", "edge", "paper", "'Vanitas' still life", "fleetingness", "painting", "brevity", "book", "death", "\u2019"], "SK-C-610": [], "SK-A-2836": [], "SK-C-291": [], "SK-A-2713": [], "SK-A-4839": ["breakfast piece (Dutch: 'ontbijtje')", "salt-cellar, salt-shaker", "salt", "glass, rummer"], "SK-A-3123": [], "SK-A-2213": ["rodents: rabbit", "carpet, rug", "monkeys, apes", "garden fountain"], "SK-A-613": ["picture", "son", "image", "insubordination", "command", "admiralty", "amsterdam", "headquarters", "consul", "story"], "SK-A-2152": ["butterflies", "layer", "impression", "transparent", "hermit", "tablecloth", "insects: grass-hopper", "s", "grasshoppers", "viewer", "crab", "glaze", "grey", "fruit", "creation", "example", "insects: butterfly", "painting", "shell", "spiders"], "SK-A-2150": ["geertgen", "painter", "asia", "jesus", "sint-jansheren", "saint", "john", "baby", "commandery", "monastery", "hail", "magi", "europe", "haarlem", "tribute", "africa"], "SK-A-3347": ["open hearth, fire-place", "dog", "backgammon, tric-trac"], "SK-A-4098": ["birds", "garden", "ornamental birds: peacock", "dog", "ornamental birds: parrot", "park"], "SK-A-2962": ["animals", "challenge", "silver", "public", "table", "fruit", "glass", "porcelain", "art", "role", "texture", "appreciation", "realism"], "SK-A-93": [], "SK-A-1130": [], "SK-A-129": ["adam", "serpent", "face", "torso", "knowledge", "fruit", "hands", "cloud", "left", "background", "tree", "paradise", "eve"], "SK-A-199": ["dutch", "watch", "fruits: lemon", "type", "porcelain", "bowl", "century", "republic", "kalf", "piece", "outside", "klapmutsen", "example", "glass of wine", "inside", "rim", "decoration"], "RP-P-2008-370": ["chair", "draughts"], "SK-A-3456": ["fruits: lemon", "(non-fruit) products of plants or trees: asparagus"], "RP-F-2004-71": [], "SK-A-2362": ["ring", "glass of beer", "turn", "century", "molluscs: oyster", "term", "feat", "glass", "type", "person", "swig", "painting", "beer", "passglas", "tobacco", "object"], "SK-A-2251": ["kitchen-interior with foodstuffs in foreground (Dutch: 'keukenstuk')", "kitchen-maid, kitchen servant"], "SK-A-2549": ["foodstuffs; still life of foodstuffs", "fruits: strawberry", "fruits: cherry", "vegetables (with NAME"], "RP-F-2014-7-1-3": ["vegetables"], "SK-A-2366": ["fruits", "still life of related objects"], "SK-A-4779": ["infidelity", "emperor", "group", "carousal, drinking-bout, orgy", "woman", "palace", "sillius", "greed", "wife", "s", "downfall", "end", "centre", "wedding", "claudius", "something", "banquet", "vine", "drinking", "merrymaking", "messalina", "adultery", "window"], "SK-A-2452": ["horse"], "RP-T-1881-A-107": ["crustaceans: crab"], "RP-T-1951-203": ["fruits: peach", "fruits: plum", "fruits: nuts"], "RP-T-1951-200": ["fruit", "fruits: peach", "fruits: plum", "fruits: cherry"], "SK-A-1107": [], "SK-C-1561": []}